pycntrparser/__init__.py
pycntrparser/args/parse.py
pycntrparser/CNTR.interp
pycntrparser/CNTR.tokens
pycntrparser/CNTRLexer.interp
pycntrparser/CNTRLexer.py
pycntrparser/CNTRLexer.tokens
pycntrparser/CNTRListener.py
pycntrparser/CNTRParser.py
pycntrparser/ErrorListener.py
pycntrparser/expand.py
pycntrparser/parse.py
pycntrparser-0.2.0.dist-info/entry_points.txt
pycntrparser-0.2.0.dist-info/LICENSE
pycntrparser-0.2.0.dist-info/METADATA
pycntrparser-0.2.0.dist-info/WHEEL
pycntrparser-0.2.0.dist-info/RECORD
